api/__init__.py
api/apps.py
api/urls.py
config/__init__.py
config/asgi.py
config/settings.py
config/urls.py
config/wsgi.py
django_oscarbot-0.85.dist-info/licenses/LICENSE
example/__init__.py
example/actions.py
example/admin.py
example/apps.py
example/models.py
example/router.py
example/tests.py
example/text_processor.py
example/views.py
example/voice_processor.py
example/migrations/__init__.py
oscarbot/__init__.py
oscarbot/action.py
oscarbot/admin.py
oscarbot/apps.py
oscarbot/bot.py
oscarbot/bot_logger.py
oscarbot/exceptions.py
oscarbot/handler.py
oscarbot/menu.py
oscarbot/message.py
oscarbot/messages.py
oscarbot/models.py
oscarbot/response.py
oscarbot/result.py
oscarbot/router.py
oscarbot/services.py
oscarbot/shortcut.py
oscarbot/structures.py
oscarbot/tests.py
oscarbot/urls.py
oscarbot/views.py
oscarbot/__pycache__/__init__.cpython-311.pyc
oscarbot/__pycache__/action.cpython-311.pyc
oscarbot/__pycache__/admin.cpython-311.pyc
oscarbot/__pycache__/apps.cpython-311.pyc
oscarbot/__pycache__/bot.cpython-311.pyc
oscarbot/__pycache__/bot_logger.cpython-311.pyc
oscarbot/__pycache__/handler.cpython-311.pyc
oscarbot/__pycache__/menu.cpython-311.pyc
oscarbot/__pycache__/messages.cpython-311.pyc
oscarbot/__pycache__/models.cpython-311.pyc
oscarbot/__pycache__/response.cpython-311.pyc
oscarbot/__pycache__/router.cpython-311.pyc
oscarbot/__pycache__/services.cpython-311.pyc
oscarbot/__pycache__/shortcut.cpython-311.pyc
oscarbot/__pycache__/structures.cpython-311.pyc
oscarbot/__pycache__/tests.cpython-311.pyc
oscarbot/__pycache__/urls.cpython-311.pyc
oscarbot/__pycache__/views.cpython-311.pyc
oscarbot/management/__init__.py
oscarbot/management/__pycache__/__init__.cpython-311.pyc
oscarbot/management/commands/__init__.py
oscarbot/management/commands/bottest.py
oscarbot/management/commands/create_bot_db.py
oscarbot/management/commands/messages.py
oscarbot/management/commands/runbot.py
oscarbot/management/commands/setwh.py
oscarbot/management/commands/__pycache__/__init__.cpython-311.pyc
django_oscarbot-0.85.dist-info/METADATA
django_oscarbot-0.85.dist-info/WHEEL
django_oscarbot-0.85.dist-info/top_level.txt
django_oscarbot-0.85.dist-info/RECORD
