Metadata-Version: 2.4
Name: django-oscarbot
Version: 0.85
Summary: Django app for create Telegram bot
Home-page: https://oscarbot.site/
Author: Oleg Maslov
Author-email: Oleg Maslov <info@oscar-studio.com>, Evgeniy Fedorin <revike@ya.ru>
License: Copyright (c) 2023 Oleg Maslov (https://oscar-studio.com/)
Project-URL: Homepage, https://github.com/oscarbotru/oscarbot
Project-URL: Bug Reports, https://github.com/oscarbotru/oscarbot/issues
Keywords: django,telegram
Classifier: Development Status :: 4 - Beta
Classifier: Environment :: Web Environment
Classifier: Framework :: Django
Classifier: Intended Audience :: Developers
Classifier: Topic :: Software Development :: Build Tools
Classifier: License :: OSI Approved :: MIT License
Classifier: Programming Language :: Python :: 3
Classifier: Programming Language :: Python :: 3.7
Classifier: Programming Language :: Python :: 3.8
Classifier: Programming Language :: Python :: 3.9
Classifier: Programming Language :: Python :: 3.10
Classifier: Programming Language :: Python :: 3.11
Classifier: Programming Language :: Python :: 3 :: Only
Requires-Python: >=3.11
License-File: LICENSE
Requires-Dist: django
Requires-Dist: requests
Requires-Dist: pyyaml
Provides-Extra: dev
Requires-Dist: check-manifest; extra == "dev"
Provides-Extra: test
Requires-Dist: coverage; extra == "test"
Dynamic: license-file
